examples/__init__.py
examples/multiple.py
examples/single.py
parallel_bars/__init__.py
parallel_bars/main.py
parallel_bars/tests/__init__.py
parallel_bars/tests/test_multiple_bars.py
parallel_bars/tests/test_single_bar.py
parallel_bars/tests/test_utils.py
parallel_bars-0.0.6.dist-info/LICENSE
parallel_bars-0.0.6.dist-info/METADATA
parallel_bars-0.0.6.dist-info/WHEEL
parallel_bars-0.0.6.dist-info/top_level.txt
parallel_bars-0.0.6.dist-info/RECORD
