Metadata-Version: 2.1
Name: parallel-bars
Version: 0.0.6
Summary: Simple wrapper on top of multiprocessing and tqdm progress bars
Home-page: https://github.com/mrapacz/parallel-bars
Author: Maciej Rapacz
Author-email: python.parallelbars@gmail.com
License: UNKNOWN
Platform: UNKNOWN
Classifier: Programming Language :: Python :: 3
Classifier: License :: OSI Approved :: MIT License
Classifier: Operating System :: OS Independent
